MANIFEST.in
README.rst
setup.cfg
setup.py
normanpg/__init__.py
normanpg/cli.py
normanpg/errors.py
normanpg/geometry.py
normanpg/pg.py
normanpg/version.py
normanpg.egg-info/PKG-INFO
normanpg.egg-info/SOURCES.txt
normanpg.egg-info/dependency_links.txt
normanpg.egg-info/entry_points.txt
normanpg.egg-info/requires.txt
normanpg.egg-info/top_level.txt
normanpg/functions/__init__.py
normanpg/functions/database.py
normanpg/functions/tables.py
normanpg/functions/database.phr/create_db.sql
normanpg/functions/database.phr/create_extension.sql
normanpg/functions/database.phr/create_schema.sql
normanpg/functions/database.phr/drop_schema.sql
normanpg/functions/database.phr/schema_exists.sql
normanpg/functions/database.phr/select_db_count.sql
normanpg/functions/tables.phr/geometry_column.sql
normanpg/functions/tables.phr/srid.sql
normanpg/functions/tables.phr/table_exists.sql