Metadata-Version: 1.2
Name: normanpg
Version: 0.0.8
Summary: This is a set of modest utilities that may be helpful when talking to PostgreSQL.
Home-page: https://github.com/patdaburu/normanpg
Author: Pat Daburu
Author-email: pat@daburu.net
License: MIT
Download-URL: https://github.com/patdaburu/normanpg/archive/0.0.8.tar.gz
Platform: UNKNOWN
Classifier: Development Status :: 3 - Alpha
Classifier: Intended Audience :: Developers
Classifier: Topic :: Software Development :: Libraries
Classifier: License :: OSI Approved :: MIT License
Classifier: Programming Language :: Python :: 3.6
Requires-Python: >=0.0.1
